doegen/Experiment_results.xlsx
doegen/Experiment_setup.xlsx
doegen/Experiment_setup_extended.xlsx
doegen/__init__.py
doegen/configloader.py
doegen/configloader_results.py
doegen/create_resultfile.py
doegen/create_setupfile.py
doegen/create_setupfile_extended.py
doegen/doegen.py
doegen/doeval.py
doegen/init_config.py
doegen/init_tests.py
doegen/settings_design.yaml
doegen/settings_expresults.yaml
doegen/test/Experiment_setup_test.xlsx
doegen/test/settings_design_test.yaml
doegen/test/settings_expresults_test.yaml
doegen/test/results/Designtable_optimal_Nrun72.csv
doegen/test/results/experiment_results_Nrun72.xlsx
DoEgen-0.5.0.dist-info/LICENSE.md
DoEgen-0.5.0.dist-info/LICENSE_old.md
DoEgen-0.5.0.dist-info/METADATA
DoEgen-0.5.0.dist-info/WHEEL
DoEgen-0.5.0.dist-info/top_level.txt
DoEgen-0.5.0.dist-info/RECORD
