Metadata-Version: 2.1
Name: DoEgen
Version: 0.5.0
Summary: DoEgen: A Python Library for Optimised Design of Experiment Generation and Evaluation
Home-page: https://github.com/sebhaan/DoEgen
Author: Sebastian Haan
Author-email: sebastian.haan@sydney.edu.au
Classifier: Programming Language :: Python :: 3
Classifier: Programming Language :: Python :: 3.6
Classifier: Programming Language :: Python :: 3.7
Requires-Python: >=3.6
License-File: LICENSE.md
License-File: LICENSE_old.md
Requires-Dist: numpy >=1.16.3
Requires-Dist: xlrd ==1.2.0
Requires-Dist: pandas >=1.0.3
Requires-Dist: XlsxWriter >=1.2.8
Requires-Dist: openpyxl >=3.0.7
Requires-Dist: seaborn >=0.11.1
Requires-Dist: OApackage >=2.7.11
Requires-Dist: tabulate >=0.8.9
Requires-Dist: matplotlib >=3.1.0
Requires-Dist: PyYAML >=5.3.1
Requires-Dist: scikit-learn >=0.22.2.post1
